examples/__init__.py
examples/nesbi-example.py
nesbi/__init__.py
nesbi/core/__init__.py
nesbi/core/configuration.py
nesbi/core/nsot.py
nesbi/core/scanner.py
nesbi/core/helpers/__init__.py
nesbi/core/helpers/logger.py
nesbi-1.0.5.dist-info/LICENSE
nesbi-1.0.5.dist-info/METADATA
nesbi-1.0.5.dist-info/WHEEL
nesbi-1.0.5.dist-info/top_level.txt
nesbi-1.0.5.dist-info/RECORD
