Metadata-Version: 2.1
Name: nesbi
Version: 1.0.5
Summary: Nesbi (Network Scan, Build and Import data)
Home-page: https://github.com/dm-drogeriemarkt/nesbi
Author: Simon Metzger
Author-email: simon.metzger@dm.de
License: MIT License
Platform: any
Classifier: Development Status :: 4 - Beta
Classifier: Programming Language :: Python :: 3
Classifier: Programming Language :: Python :: 3 :: Only
Classifier: Programming Language :: Python :: 3.7
Classifier: Programming Language :: Python :: 3.8
Classifier: Programming Language :: Python :: 3.9
Classifier: Programming Language :: Python :: 3.10
Classifier: License :: OSI Approved :: MIT License
License-File: LICENSE
Requires-Dist: napalm
Requires-Dist: requests
Requires-Dist: nelsnmp
